README.rst
setup.cfg
setup.py
pretty_freeze/__init__.py
pretty_freeze/freeze.py
pretty_freeze.egg-info/PKG-INFO
pretty_freeze.egg-info/SOURCES.txt
pretty_freeze.egg-info/dependency_links.txt
pretty_freeze.egg-info/entry_points.txt
pretty_freeze.egg-info/pbr.json
pretty_freeze.egg-info/top_level.txt