Metadata-Version: 1.1
Name: pretty-freeze
Version: 0.1.0
Summary: Pip freeze that shows detailed descriptions of the packages.
Home-page: https://github.com/Wisheri/pretty-freeze
Author: Ville Tainio
Author-email: tainio.ville@gmail.com
License: MIT
Keywords: freeze pip pretty information meta
Platform: UNKNOWN
Classifier: Development Status :: 3 - Alpha
Classifier: Intended Audience :: Developers
Classifier: Topic :: Software Development :: Build Tools
Classifier: License :: OSI Approved :: MIT License
Classifier: Programming Language :: Python :: 2
Classifier: Programming Language :: Python :: 2.6
Classifier: Programming Language :: Python :: 2.7
Classifier: Programming Language :: Python :: 3
Classifier: Programming Language :: Python :: 3.2
Classifier: Programming Language :: Python :: 3.3
Classifier: Programming Language :: Python :: 3.4
